tzxt/__init__.py
tzxt/all.py
tzxt/example.py
tzxt/ord_cut.py
tzxt-0.0.4.dist-info/METADATA
tzxt-0.0.4.dist-info/WHEEL
tzxt-0.0.4.dist-info/RECORD
