Metadata-Version: 2.3
Name: tzxt
Version: 0.0.4
Summary: A python package for personal purposes
Project-URL: Homepage, https://jhu.edu
Author-email: Example Author <NONE@example.com>
Classifier: Operating System :: OS Independent
Classifier: Programming Language :: Python :: 3
Requires-Python: >=3.8
